zmesh/__init__.py
zmesh/_zmesh.cp311-win_amd64.pyd
zmesh/_zmesh.pyx
zmesh/cMesher.hpp
zmesh/mesh.py
zmesh/utility.hpp
zmesh-1.9.0.dist-info/licenses/AUTHORS
zmesh-1.9.0.dist-info/licenses/LICENSE
zmesh-1.9.0.dist-info/METADATA
zmesh-1.9.0.dist-info/WHEEL
zmesh-1.9.0.dist-info/pbr.json
zmesh-1.9.0.dist-info/top_level.txt
zmesh-1.9.0.dist-info/RECORD
